sparkutility/__init__.py
sparkutility/is_numeric.py
sparkutility-0.1.dist-info/LICENSE
sparkutility-0.1.dist-info/METADATA
sparkutility-0.1.dist-info/WHEEL
sparkutility-0.1.dist-info/top_level.txt
sparkutility-0.1.dist-info/RECORD
